{
  "swagger": "2.0",
  "info": {
    "title": "workflow/v1/execution_service.proto",
    "version": "version not set"
  },
  "tags": [
    {
      "name": "ExecutionService"
    }
  ],
  "consumes": [
    "application/json"
  ],
  "produces": [
    "application/json"
  ],
  "paths": {},
  "definitions": {
    "commonv1Status": {
      "type": "object",
      "properties": {
        "code": {
          "type": "integer",
          "format": "int32",
          "description": "The status code, which should be an enum value of google.rpc.Code."
        },
        "message": {
          "type": "string",
          "description": "A developer-facing error message."
        },
        "details": {
          "type": "object",
          "description": "A list of messages that carry the error details."
        }
      },
      "description": "Status is a standard message for returning operation status.\nIt's modeled after google.rpc.Status."
    },
    "googlerpcStatus": {
      "type": "object",
      "properties": {
        "code": {
          "type": "integer",
          "format": "int32"
        },
        "message": {
          "type": "string"
        },
        "details": {
          "type": "array",
          "items": {
            "type": "object",
            "$ref": "#/definitions/protobufAny"
          }
        }
      }
    },
    "protobufAny": {
      "type": "object",
      "properties": {
        "@type": {
          "type": "string"
        }
      },
      "additionalProperties": {}
    },
    "protobufNullValue": {
      "type": "string",
      "enum": [
        "NULL_VALUE"
      ],
      "default": "NULL_VALUE",
      "description": "`NullValue` is a singleton enumeration to represent the null value for the\n`Value` type union.\n\nThe JSON representation for `NullValue` is JSON `null`.\n\n - NULL_VALUE: Null value."
    },
    "v1CancelExecutionResponse": {
      "type": "object",
      "properties": {
        "status": {
          "$ref": "#/definitions/commonv1Status"
        }
      }
    },
    "v1ExecutionStatus": {
      "type": "string",
      "enum": [
        "EXECUTION_STATUS_UNSPECIFIED",
        "EXECUTION_STATUS_PENDING",
        "EXECUTION_STATUS_RUNNING",
        "EXECUTION_STATUS_COMPLETED",
        "EXECUTION_STATUS_FAILED",
        "EXECUTION_STATUS_CANCELLED"
      ],
      "default": "EXECUTION_STATUS_UNSPECIFIED",
      "description": "ExecutionStatus represents the lifecycle status of a workflow run."
    },
    "v1GetExecutionResponse": {
      "type": "object",
      "properties": {
        "execution": {
          "$ref": "#/definitions/v1WorkflowExecution"
        }
      }
    },
    "v1ListExecutionsResponse": {
      "type": "object",
      "properties": {
        "executions": {
          "type": "array",
          "items": {
            "type": "object",
            "$ref": "#/definitions/v1WorkflowExecution"
          }
        },
        "pagination": {
          "$ref": "#/definitions/v1PaginationResult"
        }
      }
    },
    "v1PaginationParams": {
      "type": "object",
      "properties": {
        "page": {
          "type": "integer",
          "format": "int32",
          "description": "The page number, 1-based."
        },
        "pageSize": {
          "type": "integer",
          "format": "int32",
          "description": "The number of items to return per page."
        }
      },
      "description": "PaginationParams defines parameters for paginated requests."
    },
    "v1PaginationResult": {
      "type": "object",
      "properties": {
        "page": {
          "type": "integer",
          "format": "int32",
          "description": "The current page number, 1-based."
        },
        "pageSize": {
          "type": "integer",
          "format": "int32",
          "description": "The number of items returned per page."
        },
        "totalItems": {
          "type": "integer",
          "format": "int32",
          "description": "The total number of items available."
        },
        "totalPages": {
          "type": "integer",
          "format": "int32",
          "description": "The total number of pages available."
        }
      },
      "description": "PaginationResult provides metadata for paginated responses."
    },
    "v1StartExecutionResponse": {
      "type": "object",
      "properties": {
        "execution": {
          "$ref": "#/definitions/v1WorkflowExecution"
        }
      }
    },
    "v1StreamExecutionResponse": {
      "type": "object",
      "properties": {
        "update": {
          "$ref": "#/definitions/v1WorkflowExecutionUpdate"
        }
      },
      "description": "Response for streaming workflow execution updates."
    },
    "v1WorkflowExecution": {
      "type": "object",
      "properties": {
        "id": {
          "type": "string"
        },
        "userId": {
          "type": "string"
        },
        "workflowId": {
          "type": "string"
        },
        "workflowVersion": {
          "type": "integer",
          "format": "int32"
        },
        "status": {
          "$ref": "#/definitions/v1ExecutionStatus"
        },
        "context": {
          "type": "object",
          "description": "The current state/context of the workflow."
        },
        "output": {
          "type": "object",
          "description": "The final output of the workflow."
        },
        "error": {
          "$ref": "#/definitions/commonv1Status",
          "description": "Detailed error information if the execution failed."
        },
        "createdAt": {
          "type": "string",
          "format": "date-time"
        },
        "startedAt": {
          "type": "string",
          "format": "date-time"
        },
        "completedAt": {
          "type": "string",
          "format": "date-time"
        }
      },
      "description": "WorkflowExecution represents a single run of a workflow."
    },
    "v1WorkflowExecutionUpdate": {
      "type": "object",
      "properties": {
        "executionId": {
          "type": "string"
        },
        "status": {
          "$ref": "#/definitions/v1ExecutionStatus"
        },
        "contextDelta": {
          "type": "object",
          "description": "A partial update to the workflow's context."
        },
        "timestamp": {
          "type": "string",
          "format": "date-time"
        },
        "isFinal": {
          "type": "boolean",
          "description": "Set to true in the final message of the stream."
        }
      },
      "description": "WorkflowExecutionUpdate is a message for streaming real-time updates of a run."
    }
  }
}
